pykal_core/__init__.py
pykal_core-0.1.dist-info/METADATA
pykal_core-0.1.dist-info/WHEEL
pykal_core-0.1.dist-info/top_level.txt
pykal_core-0.1.dist-info/RECORD
