Metadata-Version: 2.4
Name: pykal_core
Version: 0.1
Summary: pykal_core is a Python library for modeling general control systems.
Author-email: Nehal Singh Mangat <nehalsinghmangat.software@gmail.com>
License-Expression: MIT
Project-URL: Homepage, https://github.com/nehalsinghmangat/pykal_core
Project-URL: Documentation, https://pykal_core.readthedocs.io
Keywords: kalman,filter,estimation
Requires-Python: >=3.12
Requires-Dist: numpy>=2.3.0
Requires-Dist: pandas>=2.3.0
Requires-Dist: matplotlib>=3.10.3
Requires-Dist: scipy>=1.15.3
Provides-Extra: dev
Requires-Dist: pytest>=7.0; extra == "dev"
Requires-Dist: pytest-doctestplus>=1.0.0; extra == "dev"
Requires-Dist: pytest-cov; extra == "dev"
Requires-Dist: coverage[toml]; extra == "dev"
Requires-Dist: flake8>=6.0; extra == "dev"
Requires-Dist: black>=24.0; extra == "dev"
Requires-Dist: isort>=6.0; extra == "dev"
Requires-Dist: pylint; extra == "dev"
Requires-Dist: mypy>=1.0; extra == "dev"
Requires-Dist: pre-commit>=3.0; extra == "dev"
Requires-Dist: build>=0.10; extra == "dev"
Requires-Dist: twine>=4.0; extra == "dev"
Requires-Dist: setuptools-scm>=7.0; extra == "dev"
Requires-Dist: sphinx>=8.0; extra == "dev"
Requires-Dist: sphinx-rtd-theme>=1.3; extra == "dev"
Requires-Dist: nbsphinx>=0.9.7; extra == "dev"
Requires-Dist: myst-parser>=1.0; extra == "dev"
Requires-Dist: sphinx-toolbox>=3.5; extra == "dev"
Requires-Dist: graphviz; extra == "dev"
